MANIFEST.in
README.md
pamphlet.py
pamphlet_cffi.py
setup.py
examples/login
examples/passwd
examples/sshd
pamphlet.egg-info/PKG-INFO
pamphlet.egg-info/SOURCES.txt
pamphlet.egg-info/dependency_links.txt
pamphlet.egg-info/requires.txt
pamphlet.egg-info/top_level.txt
test/Makefile
test/__init__.py
test/fake_open.c
test/test_auth.py
test/test_import.py
test/etc/group
test/etc/gshadow
test/etc/passwd
test/etc/shadow
test/etc/pam.d/other