Metadata-Version: 1.1
Name: pamphlet
Version: 1.3
Summary: Linux PAM bindings for python
Home-page: http://github.com/seveas/pamphlet
Author: Dennis Kaarsemaker
Author-email: dennis@kaarsemaker.net
License: UNKNOWN
Platform: UNKNOWN
Classifier: Development Status :: 3 - Alpha
Classifier: Intended Audience :: Developers
Classifier: License :: OSI Approved :: zlib/libpng License
Classifier: Programming Language :: Python
Classifier: Programming Language :: Python :: 3
